colorate_console/__init__.py
colorate_console/colorizer.py
colorate_console-0.3.6.dist-info/METADATA
colorate_console-0.3.6.dist-info/WHEEL
colorate_console-0.3.6.dist-info/entry_points.txt
colorate_console-0.3.6.dist-info/top_level.txt
colorate_console-0.3.6.dist-info/RECORD
