Metadata-Version: 2.1
Name: colorate_console
Version: 0.3.6
Summary: Colorateur de textes dans un terminal
Home-page: https://github.com/bouquet-cedric/module-python
Author: Bouquet Cédric
Author-email: cedric-bouquet-7@outlook.fr
Classifier: Programming Language :: Python :: 3
Requires-Python: >=3.0
